microsoft_fabric_api/__init__.py
microsoft_fabric_api/client.py
microsoft_fabric_api/fabric_api_utils.py
microsoft_fabric_api/extensions/admin/__init__.py
microsoft_fabric_api/extensions/admin/_client.py
microsoft_fabric_api/extensions/admin/_patch.py
microsoft_fabric_api/extensions/admin/operations/__init__.py
microsoft_fabric_api/extensions/admin/operations/_operations.py
microsoft_fabric_api/extensions/admin/operations/_patch.py
microsoft_fabric_api/extensions/apacheairflowjob/__init__.py
microsoft_fabric_api/extensions/apacheairflowjob/_client.py
microsoft_fabric_api/extensions/apacheairflowjob/_patch.py
microsoft_fabric_api/extensions/apacheairflowjob/operations/__init__.py
microsoft_fabric_api/extensions/apacheairflowjob/operations/_operations.py
microsoft_fabric_api/extensions/apacheairflowjob/operations/_patch.py
microsoft_fabric_api/extensions/copyjob/__init__.py
microsoft_fabric_api/extensions/copyjob/_client.py
microsoft_fabric_api/extensions/copyjob/_patch.py
microsoft_fabric_api/extensions/copyjob/operations/__init__.py
microsoft_fabric_api/extensions/copyjob/operations/_operations.py
microsoft_fabric_api/extensions/copyjob/operations/_patch.py
microsoft_fabric_api/extensions/core/__init__.py
microsoft_fabric_api/extensions/core/_client.py
microsoft_fabric_api/extensions/core/_patch.py
microsoft_fabric_api/extensions/core/operations/__init__.py
microsoft_fabric_api/extensions/core/operations/_operations.py
microsoft_fabric_api/extensions/core/operations/_patch.py
microsoft_fabric_api/extensions/dashboard/__init__.py
microsoft_fabric_api/extensions/dashboard/_client.py
microsoft_fabric_api/extensions/dashboard/_patch.py
microsoft_fabric_api/extensions/dataflow/__init__.py
microsoft_fabric_api/extensions/dataflow/_client.py
microsoft_fabric_api/extensions/dataflow/_patch.py
microsoft_fabric_api/extensions/dataflow/operations/__init__.py
microsoft_fabric_api/extensions/dataflow/operations/_operations.py
microsoft_fabric_api-0.1.0b1.dist-info/licenses/assets/LICENSE.txt
microsoft_fabric_api-0.1.0b1.dist-info/METADATA
microsoft_fabric_api-0.1.0b1.dist-info/WHEEL
microsoft_fabric_api-0.1.0b1.dist-info/top_level.txt
microsoft_fabric_api-0.1.0b1.dist-info/RECORD
