Metadata-Version: 2.4
Name: microsoft-fabric-api
Version: 0.1.0b1
Summary: Microsoft Fabric API Python SDK
Author: Microsoft Corporation
Project-URL: Homepage, https://learn.microsoft.com/en-us/rest/api/fabric
Keywords: fabric,fabric sdk,microsoft,azure
Classifier: Development Status :: 4 - Beta
Classifier: Programming Language :: Python :: 3
Classifier: Programming Language :: Python :: 3.8
Classifier: Programming Language :: Python :: 3.9
Classifier: Programming Language :: Python :: 3.10
Classifier: Programming Language :: Python :: 3.11
Classifier: Programming Language :: Python :: 3.12
Classifier: License :: OSI Approved :: MIT License
Classifier: Operating System :: OS Independent
Requires-Python: >=3.8
License-File: assets/LICENSE.txt
Requires-Dist: isodate<1.0.0,>=0.6.1
Requires-Dist: azure-core<2.0.0,>=1.24.0
Dynamic: license-file
